pyjamalib/DataAnalysis.py
pyjamalib/DataExample.py
pyjamalib/DataHandler.py
pyjamalib/DataPlot.py
pyjamalib/DataProcessing.py
pyjamalib/DataVisualisation.py
pyjamalib/IMUDataProcessing.py
pyjamalib/__init__.py
pyjamalib-1.0.0.dist-info/LICENSE
pyjamalib-1.0.0.dist-info/METADATA
pyjamalib-1.0.0.dist-info/WHEEL
pyjamalib-1.0.0.dist-info/top_level.txt
pyjamalib-1.0.0.dist-info/RECORD
