Metadata-Version: 2.1
Name: pyjamalib
Version: 1.0.0
Summary: A library for analyze joint angles from IMU data
Home-page: https://github.com/tuliofalmeida/pyjama
Author: Túlio 1F. Almeida
Author-email: tuliofalmeida@hotmail.com
License: MIT
Platform: UNKNOWN
Classifier: Programming Language :: Python :: 3.8
Classifier: License :: OSI Approved :: MIT License
Classifier: Operating System :: OS Independent
Requires-Dist: numpy
Requires-Dist: pandas
Requires-Dist: matplotlib
